easyAE/AE.py
easyAE/__init__.py
easyAE_samuel.revolinski-0.0.0.dist-info/METADATA
easyAE_samuel.revolinski-0.0.0.dist-info/RECORD
easyAE_samuel.revolinski-0.0.0.dist-info/WHEEL
easyAE_samuel.revolinski-0.0.0.dist-info/top_level.txt
