Metadata-Version: 2.1
Name: easyAE-samuel.revolinski
Version: 0.0.0
Summary: easy way for non-linear dimensionality increase or reduction
Home-page: https://github.com/Zhiwu-Zhang-Lab/genetic_spectral_AutoEncoder
Author: Samuel Revolinski
Author-email: samuel.revolinski@wsu.edu
License: UNKNOWN
Platform: UNKNOWN
Classifier: Programming Language :: Python :: 3
Classifier: License :: OSI Approved :: MIT License
Classifier: Operating System :: OS Independent
